jadukor/__init__.py
jadukor-0.0.8.dist-info/LICENSE.txt
jadukor-0.0.8.dist-info/METADATA
jadukor-0.0.8.dist-info/WHEEL
jadukor-0.0.8.dist-info/top_level.txt
jadukor-0.0.8.dist-info/RECORD
