Metadata-Version: 2.1
Name: jadukor
Version: 0.0.8
Summary: The most powerfull module in the universe
Home-page: http://github.com/atmragib/jadukor
Author: A T M Ragib Raihan
Author-email: atmragibraihan@gmail.com
License: MIT
Download-URL: http://github.com/atmragib/jadukor/archive/v0.0.8.tar.gz
Keywords: personal,handy,ragib,jadukor
Platform: UNKNOWN
Classifier: Development Status :: 3 - Alpha
Classifier: Intended Audience :: Developers
Classifier: Topic :: Software Development :: Build Tools
Classifier: License :: OSI Approved :: MIT License
Classifier: Operating System :: OS Independent
Classifier: Programming Language :: Python :: 3
Classifier: Programming Language :: Python :: 3.4
Classifier: Programming Language :: Python :: 3.5
Classifier: Programming Language :: Python :: 3.6
Classifier: Programming Language :: Python :: 3.7
Classifier: Programming Language :: Python :: 3.8
Requires-Python: >=3.1
Requires-Dist: validators
Requires-Dist: beautifulsoup4
